{
    "name": "GitLeaks",
    "description": "Audit git repos for secrets. Gitleaks provides a way for you to find unencrypted secrets and other unwanted data types in git repositories.",
    "tags": [
        "secrets-management",
        "security-scanning",
        "security-auditing",
        "golang"
    ],
    "operating_systems": [
        "linux",
        "mac",
        "windows"
    ],
    "license": "MIT",
    "availability": [
        "opensource"
    ],
    "github_url": "https://github.com/zricethezav/gitleaks",
    "url": "https://github.com/zricethezav/gitleaks"
}