{
    "name": "Terraform Compliance",
    "description": "A lightweight, security focused, BDD test framework against terraform. terraform-compliance is a lightweight, security and compliance focused test framework against terraform to enable negative testing capability for your infrastructure-as-code.",
    "tags": [
        "cloud-security",
        "security-linter",
        "terraform",
        "static-analysis",
        "continuous-security",
        "compliance",
        "iaac"
    ],
    "operating_systems": [
        "linux",
        "windows",
        "mac"
    ],
    "license": "MIT",
    "availability": [
        "opensource"
    ],
    "github_url": "https://github.com/eerkunt/terraform-compliance",
    "url": "https://terraform-compliance.com/"
}